{"stats":{"minecraft:picked_up":{"minecraft:crafting_table":1,"minecraft:leather":3,"minecraft:acacia_log":7,"minecraft:porkchop":10,"minecraft:oak_log":15,"minecraft:arrow":1,"minecraft:bone":3,"minecraft:stone_axe":1,"minecraft:wheat_seeds":4,"minecraft:beef":5,"minecraft:iron_ore":31,"minecraft:poppy":2,"minecraft:oak_sapling":2,"minecraft:sugar_cane":9,"minecraft:mutton":7,"minecraft:coal":24,"minecraft:white_wool":6,"minecraft:cobblestone":34,"minecraft:egg":1},"minecraft:custom":{"minecraft:time_since_rest":15541,"minecraft:interact_with_furnace":6,"minecraft:sprint_one_cm":27981,"minecraft:damage_taken":120,"minecraft:walk_one_cm":27153,"minecraft:mob_kills":17,"minecraft:damage_dealt":1820,"minecraft:swim_one_cm":7481,"minecraft:interact_with_crafting_table":5,"minecraft:fly_one_cm":46910,"minecraft:crouch_one_cm":1253,"minecraft:play_one_minute":15541,"minecraft:sneak_time":931,"minecraft:walk_under_water_one_cm":241,"minecraft:jump":366,"minecraft:leave_game":2,"minecraft:time_since_death":15541,"minecraft:walk_on_water_one_cm":1732,"minecraft:fall_one_cm":7073},"minecraft:crafted":{"minecraft:cooked_beef":2,"minecraft:oak_planks":60,"minecraft:crafting_table":1,"minecraft:stick":4,"minecraft:wooden_pickaxe":1,"minecraft:stone_pickaxe":1,"minecraft:furnace":2,"minecraft:air":0},"minecraft:killed":{"minecraft:sheep":6,"minecraft:skeleton":3,"minecraft:pig":5,"minecraft:cow":3},"minecraft:used":{"minecraft:stone_pickaxe":61,"minecraft:poppy":2,"minecraft:wooden_pickaxe":3,"minecraft:stone_axe":28,"minecraft:beef":1,"minecraft:crafting_table":2,"minecraft:furnace":2,"minecraft:porkchop":2,"minecraft:cooked_beef":2},"minecraft:mined":{"minecraft:iron_ore":8,"minecraft:crafting_table":1,"minecraft:grass":36,"minecraft:acacia_log":7,"minecraft:coal_ore":24,"minecraft:oak_log":10,"minecraft:poppy":2,"minecraft:tall_grass":1,"minecraft:stone":32,"minecraft:sugar_cane":4,"minecraft:oak_leaves":1}},"DataVersion":2586}